README.md
setup.py
catchphrase/__init__.py
catchphrase/batman.py
catchphrase.egg-info/PKG-INFO
catchphrase.egg-info/SOURCES.txt
catchphrase.egg-info/dependency_links.txt
catchphrase.egg-info/top_level.txt