Metadata-Version: 2.1
Name: catchphrase
Version: 0.1.0
Summary: Holy Hooligan Coders, Batman! A python package for generating/retrieving common catchphrases!
Home-page: https://github.com/scnerd/catchphrase
Author: David Maxson
Author-email: scnerd@gmail.com
License: MIT
Platform: UNKNOWN
